Metadata-Version: 2.1
Name: Text2CArray
Version: 0.1.0
Summary: Script for generating C arrays from text.
Home-page: https://github.com/ProrokWielki/Text2CArray
Author: Pawel Warzecha
Author-email: pawel.warzecha@yahoo.com
License: MIT
Platform: UNKNOWN
